<?xml version="1.0" encoding="utf-8"?>
<SdkMessageProcessingStep Name="TC.PowerApps.FDR.CustomActions.Operations.ListOfOperationsPost: fdr_Operations4SRF of any Entity" SdkMessageProcessingStepId="{3725822c-923e-ed11-bba2-0022483d0343}" xmlns:xsi="http://www.w3.org/2001/XMLSchema-instance">
  <SdkMessageId>5c8bb2e1-8c3e-ed11-bba2-0022483d0343</SdkMessageId>
  <PluginTypeName>TC.PowerApps.FDR.CustomActions.Operations.ListOfOperationsPost, TC.PowerApps.FDR.CustomActions, Version=1.0.0.0, Culture=neutral, PublicKeyToken=d339dc25e504ddc1</PluginTypeName>
  <PluginTypeId>e5cc95d6-fe55-4bc8-a36d-23f4b15e2bb9</PluginTypeId>
  <AsyncAutoDelete>0</AsyncAutoDelete>
  <Description>TC.PowerApps.FDR.CustomActions.Operations.ListOfOperationsPost: fdr_Operations4SRF of any Entity</Description>
  <FilteringAttributes></FilteringAttributes>
  <InvocationSource>0</InvocationSource>
  <Mode>0</Mode>
  <Rank>1</Rank>
  <EventHandlerTypeCode>4602</EventHandlerTypeCode>
  <Stage>40</Stage>
  <IsCustomizable>1</IsCustomizable>
  <IsHidden>0</IsHidden>
  <SupportedDeployment>0</SupportedDeployment>
  <IntroducedVersion>1.0</IntroducedVersion>
  <SdkMessageProcessingStepImages />
</SdkMessageProcessingStep>