<?xml version="1.0" encoding="utf-8"?>
<WebResource xmlns:xsi="http://www.w3.org/2001/XMLSchema-instance">
  <WebResourceId>{9659cf64-f359-ed11-9562-0022483d0c87}</WebResourceId>
  <Name>cid_tdgcore_invitation.js</Name>
  <DisplayName>tdgcore_invitation.js</DisplayName>
  <LanguageCode>0</LanguageCode>
  <WebResourceType>3</WebResourceType>
  <IntroducedVersion>1.0.0.0</IntroducedVersion>
  <IsEnabledForMobileClient>0</IsEnabledForMobileClient>
  <IsAvailableForMobileOffline>0</IsAvailableForMobileOffline>
  <DependencyXml>&lt;Dependencies&gt;&lt;Dependency componentType="WebResource"/&gt;&lt;/Dependencies&gt;</DependencyXml>
  <IsCustomizable>1</IsCustomizable>
  <CanBeDeleted>1</CanBeDeleted>
  <IsHidden>0</IsHidden>
  <FileName>/WebResources/cid_tdgcore_invitationjs9659CF64-F359-ED11-9562-0022483D0C87</FileName>
</WebResource>