<?xml version="1.0" encoding="utf-8"?>
<EntityRelationships xmlns:xsi="http://www.w3.org/2001/XMLSchema-instance">
  <EntityRelationship Name="business_unit_ovs_tyrational" />
  <EntityRelationship Name="business_unit_tc_tcfiscalquarter" />
  <EntityRelationship Name="lk_ovs_tyrational_createdby" />
  <EntityRelationship Name="lk_ovs_tyrational_modifiedby" />
  <EntityRelationship Name="lk_tc_tcfiscalquarter_createdby" />
  <EntityRelationship Name="lk_tc_tcfiscalquarter_modifiedby" />
  <EntityRelationship Name="ovs_msdyn_workorder_FiscalQuarter_tc_TCFiscal" />
  <EntityRelationship Name="ovs_msdyn_workorder_PrimaryInspector_Bookable" />
  <EntityRelationship Name="ovs_msdyn_workorder_SecondaryInspector_Bookab" />
  <EntityRelationship Name="owner_ovs_tyrational" />
  <EntityRelationship Name="owner_tc_tcfiscalquarter" />
  <EntityRelationship Name="tc_TCFiscalQuarter_TCFiscalYear" />
  <EntityRelationship Name="team_ovs_tyrational" />
  <EntityRelationship Name="team_tc_tcfiscalquarter" />
  <EntityRelationship Name="user_ovs_tyrational" />
  <EntityRelationship Name="user_tc_tcfiscalquarter" />
</EntityRelationships>